{
  "version": 1,
  "author": "Anonymous maker",
  "editor": "wokwi",
  "parts": [
    { "type": "wokwi-breadboard", "id": "bb1", "top": -233.4, "left": -45.2, "attrs": {} },
    { "type": "wokwi-arduino-mega", "id": "mega", "top": 39, "left": -90, "attrs": {} },
    { "type": "wokwi-lcd1602", "id": "lcd1", "top": -313.37, "left": -51.2, "attrs": {} },
    { "type": "wokwi-potentiometer", "id": "pot1", "top": -241.3, "left": 268.6, "attrs": {} },
    {
      "type": "wokwi-membrane-keypad",
      "id": "keypad1",
      "top": -232.4,
      "left": 639.2,
      "attrs": {}
    },
    {
      "type": "wokwi-buzzer",
      "id": "bz1",
      "top": 223.2,
      "left": -65.4,
      "attrs": { "volume": "0.1" }
    },
    {
      "type": "wokwi-rgb-led",
      "id": "rgb1",
      "top": -140,
      "left": 183.5,
      "attrs": { "common": "cathode" }
    },
    {
      "type": "wokwi-pir-motion-sensor",
      "id": "pir1",
      "top": -255.2,
      "left": 491.82,
      "attrs": {}
    },
    {
      "type": "wokwi-photoresistor-sensor",
      "id": "ldr1",
      "top": -288.3,
      "left": 368.9,
      "rotate": 90,
      "attrs": {}
    },
    {
      "type": "wokwi-dht22",
      "id": "dht1",
      "top": -297.3,
      "left": 349.8,
      "attrs": { "temperature": "11.3", "humidity": "86" }
    }
  ],
  "connections": [
    [ "lcd1:VSS", "bb1:bn.1", "black", [ "v0" ] ],
    [ "lcd1:VDD", "bb1:bp.1", "red", [ "v0" ] ],
    [ "bb1:4t.b", "mega:12", "#8f4814", [ "v182.4", "h38.4" ] ],
    [ "lcd1:RW", "bb1:bn.3", "black", [ "v0" ] ],
    [ "lcd1:E", "mega:11", "blue", [ "v182.4", "h29.2" ] ],
    [ "lcd1:D4", "mega:5", "green", [ "v201.6", "h42.7" ] ],
    [ "lcd1:D5", "mega:4", "gold", [ "v192", "h42.7" ] ],
    [ "lcd1:D6", "mega:3", "violet", [ "v182.4", "h42.7" ] ],
    [ "lcd1:D7", "mega:2", "cyan", [ "v172.8", "h42.7" ] ],
    [ "lcd1:A", "bb1:bp.11", "red", [ "v0" ] ],
    [ "lcd1:K", "bb1:bn.12", "black", [ "v0" ] ],
    [ "mega:5V.1", "bb1:bp.24", "red", [ "v0" ] ],
    [ "mega:GND.5", "bb1:bn.26", "black", [ "v0.95", "h26.2" ] ],
    [ "pot1:GND", "bb1:bn.27", "black", [ "v0" ] ],
    [ "pot1:VCC", "bb1:bp.29", "red", [ "v0" ] ],
    [ "keypad1:R1", "mega:32", "green", [ "v0" ] ],
    [ "keypad1:R2", "mega:34", "green", [ "v9.6", "h-10" ] ],
    [ "mega:36", "keypad1:R3", "green", [ "v1.3", "h487.4" ] ],
    [ "keypad1:R4", "mega:38", "green", [ "v28.8", "h-0.2" ] ],
    [ "mega:40", "keypad1:C1", "purple", [ "v1.25", "h506.6" ] ],
    [ "keypad1:C2", "mega:42", "purple", [ "v48" ] ],
    [ "keypad1:C3", "mega:44", "purple", [ "v57.6", "h-9.75" ] ],
    [ "keypad1:C4", "mega:46", "purple", [ "v67.2", "h-0.3" ] ],
    [ "bz1:1", "mega:GND.3", "black", [ "v9.6", "h124.8" ] ],
    [ "mega:22", "bz1:2", "magenta", [ "v1.1", "h55.4", "v240" ] ],
    [ "bb1:3t.c", "bb1:35t.d", "magenta", [ "v0" ] ],
    [ "rgb1:COM", "mega:GND.1", "black", [ "v114.8", "h-172.7" ] ],
    [ "ldr1:AO", "mega:A1", "yellow", [ "v412.8", "h-316.1" ] ],
    [ "ldr1:GND", "mega:GND.5", "black", [ "v0" ] ],
    [ "ldr1:VCC", "mega:5V.2", "red", [ "v0" ] ],
    [ "pir1:VCC", "mega:5V.2", "red", [ "v0" ] ],
    [ "pir1:GND", "mega:GND.5", "black", [ "v0" ] ],
    [ "pir1:OUT", "mega:27", "purple", [ "v240", "h-28.94" ] ],
    [ "bb1:bp.23", "bb1:bp.26", "red", [ "v0" ] ],
    [ "rgb1:R", "mega:10", "red", [ "v76.8", "h-38.4" ] ],
    [ "rgb1:G", "mega:9", "orange", [ "v86.4", "h-56.3" ] ],
    [ "rgb1:B", "mega:8", "blue", [ "v96", "h-46.4" ] ],
    [ "dht1:GND", "mega:GND.4", "black", [ "v57.6", "h-38.4", "v335.05" ] ],
    [ "dht1:VCC", "mega:5V", "red", [ "v432", "h-288" ] ],
    [ "dht1:SDA", "mega:A0", "blue", [ "v441.6", "h-249.5" ] ],
    [ "lcd1:VSS", "bb1:1t.a", "", [ "$bb" ] ],
    [ "lcd1:VDD", "bb1:2t.a", "", [ "$bb" ] ],
    [ "lcd1:V0", "bb1:3t.a", "", [ "$bb" ] ],
    [ "lcd1:RS", "bb1:4t.a", "", [ "$bb" ] ],
    [ "lcd1:RW", "bb1:5t.a", "", [ "$bb" ] ],
    [ "lcd1:E", "bb1:6t.a", "", [ "$bb" ] ],
    [ "lcd1:D0", "bb1:7t.a", "", [ "$bb" ] ],
    [ "lcd1:D1", "bb1:8t.a", "", [ "$bb" ] ],
    [ "lcd1:D2", "bb1:9t.a", "", [ "$bb" ] ],
    [ "lcd1:D3", "bb1:10t.a", "", [ "$bb" ] ],
    [ "lcd1:D4", "bb1:11t.a", "", [ "$bb" ] ],
    [ "lcd1:D5", "bb1:12t.a", "", [ "$bb" ] ],
    [ "lcd1:D6", "bb1:13t.a", "", [ "$bb" ] ],
    [ "lcd1:D7", "bb1:14t.a", "", [ "$bb" ] ],
    [ "lcd1:A", "bb1:15t.a", "", [ "$bb" ] ],
    [ "lcd1:K", "bb1:16t.a", "", [ "$bb" ] ],
    [ "pot1:GND", "bb1:34t.b", "", [ "$bb" ] ],
    [ "pot1:SIG", "bb1:35t.b", "", [ "$bb" ] ],
    [ "pot1:VCC", "bb1:36t.b", "", [ "$bb" ] ],
    [ "dht1:VCC", "bb1:41t.a", "", [ "$bb" ] ],
    [ "dht1:SDA", "bb1:42t.a", "", [ "$bb" ] ],
    [ "dht1:NC", "bb1:43t.a", "", [ "$bb" ] ],
    [ "dht1:GND", "bb1:44t.a", "", [ "$bb" ] ],
    [ "rgb1:R", "bb1:23b.h", "", [ "$bb" ] ],
    [ "rgb1:COM", "bb1:24b.i", "", [ "$bb" ] ],
    [ "rgb1:G", "bb1:25b.h", "", [ "$bb" ] ],
    [ "rgb1:B", "bb1:26b.h", "", [ "$bb" ] ],
    [ "pir1:VCC", "bb1:58t.c", "", [ "$bb" ] ],
    [ "pir1:OUT", "bb1:59t.c", "", [ "$bb" ] ],
    [ "pir1:GND", "bb1:60t.c", "", [ "$bb" ] ],
    [ "ldr1:VCC", "bb1:52t.b", "", [ "$bb" ] ],
    [ "ldr1:GND", "bb1:51t.b", "", [ "$bb" ] ],
    [ "ldr1:DO", "bb1:50t.b", "", [ "$bb" ] ],
    [ "ldr1:AO", "bb1:49t.b", "", [ "$bb" ] ]
  ],
  "dependencies": {}
}